Datasnakes/__init__.py
Datasnakes/Cookies/README.md
Datasnakes/Cookies/__init__.py
Datasnakes/Cookies/__pycache__/__init__.cpython-36.pyc
Datasnakes/Cookies/new_app/__init__.py
Datasnakes/Cookies/new_app/cookiecutter.json
Datasnakes/Cookies/new_app/hooks/new_app.py
Datasnakes/Cookies/new_app/{{ cookiecutter.app_name }}/global.R
Datasnakes/Cookies/new_app/{{ cookiecutter.app_name }}/index.html
Datasnakes/Cookies/new_app/{{ cookiecutter.app_name }}/server.R
Datasnakes/Cookies/new_app/{{ cookiecutter.app_name }}/ui.R
Datasnakes/Cookies/new_app/{{ cookiecutter.app_name }}/data/.gitkeep
Datasnakes/Cookies/new_app/{{ cookiecutter.app_name }}/scripts/.gitkeep
Datasnakes/Cookies/new_app/{{ cookiecutter.app_name }}/tests/.gitkeep
Datasnakes/Cookies/new_app/{{ cookiecutter.app_name }}/www/.gitkeep
Datasnakes/Cookies/new_database/__init__.py
Datasnakes/Cookies/new_database/cookiecutter.json
Datasnakes/Cookies/new_database/hooks/new_db.py
Datasnakes/Cookies/new_database/{{ cookiecutter.db_name }}/.gitkeep
Datasnakes/Cookies/new_database/{{ cookiecutter.db_name }}/archive/.gitkeep
Datasnakes/Cookies/new_project/__init__.py
Datasnakes/Cookies/new_project/cookiecutter.json
Datasnakes/Cookies/new_project/hooks/post_gen_project.py
Datasnakes/Cookies/new_project/{{ cookiecutter.project_name }}/.gitkeep
Datasnakes/Cookies/new_project/{{ cookiecutter.project_name }}/archive/.gitkeep
Datasnakes/Cookies/new_repository/__init__.py
Datasnakes/Cookies/new_repository/cookiecutter.json
Datasnakes/Cookies/new_repository/hooks/imports.py
Datasnakes/Cookies/new_repository/{{ cookiecutter.repository_name }}/.gitignore
Datasnakes/Cookies/new_repository/{{ cookiecutter.repository_name }}/__init__.py
Datasnakes/Cookies/new_repository/{{ cookiecutter.repository_name }}/setup.py
Datasnakes/Cookies/new_repository/{{ cookiecutter.repository_name }}/docs/.gitkeep
Datasnakes/Cookies/new_repository/{{ cookiecutter.repository_name }}/docs/Phylogenetic Analysis Flowchart.pdf
Datasnakes-0.1.1a1.dist-info/DESCRIPTION.rst
Datasnakes-0.1.1a1.dist-info/METADATA
Datasnakes-0.1.1a1.dist-info/RECORD
Datasnakes-0.1.1a1.dist-info/WHEEL
Datasnakes-0.1.1a1.dist-info/entry_points.txt
Datasnakes-0.1.1a1.dist-info/metadata.json
Datasnakes-0.1.1a1.dist-info/top_level.txt
