Metadata-Version: 2.0
Name: Datasnakes
Version: 0.1.1a1
Summary: This package helps in the analysis of orthologous genes.
Home-page: https://github.com/datasnakes/Datasnakes-Scripts
Author: Rob Gilmore & Shaurita Hutchins
Author-email: UNKNOWN
License: MIT
